llama_prompt_ops/__init__.py
llama_prompt_ops/core/__init__.py
llama_prompt_ops/core/datasets.py
llama_prompt_ops/core/evaluation.py
llama_prompt_ops/core/exceptions.py
llama_prompt_ops/core/metrics.py
llama_prompt_ops/core/migrator.py
llama_prompt_ops/core/model.py
llama_prompt_ops/core/model_strategies.py
llama_prompt_ops/core/prompt_processors.py
llama_prompt_ops/core/prompt_strategies.py
llama_prompt_ops/core/utils/__init__.py
llama_prompt_ops/core/utils/format_utils.py
llama_prompt_ops/core/utils/llama_utils.py
llama_prompt_ops/core/utils/logging.py
llama_prompt_ops/core/utils/strategy_utils.py
llama_prompt_ops/core/utils/summary_utils.py
llama_prompt_ops/core/utils/telemetry.py
llama_prompt_ops/datasets/__init__.py
llama_prompt_ops/datasets/dox/__init__.py
llama_prompt_ops/datasets/dox/adapter.py
llama_prompt_ops/datasets/hotpotqa/__init__.py
llama_prompt_ops/datasets/hotpotqa/adapter.py
llama_prompt_ops/datasets/hotpotqa/metric.py
llama_prompt_ops/datasets/joule/__init__.py
llama_prompt_ops/datasets/joule/adapter.py
llama_prompt_ops/debug/__init__.py
llama_prompt_ops/interfaces/__init__.py
llama_prompt_ops/interfaces/cli.py
llama_prompt_ops/templates/__init__.py
llama_prompt_ops/templates/sample_dataset.json
llama_prompt_ops/templates/sample_prompt.txt
llama_prompt_ops/templates/__pycache__/__init__.cpython-310.pyc
llama_prompt_ops/templates/__pycache__/__init__.cpython-312.pyc
llama_prompt_ops-0.0.8.dist-info/licenses/LICENSE
llama_prompt_ops-0.0.8.dist-info/METADATA
llama_prompt_ops-0.0.8.dist-info/WHEEL
llama_prompt_ops-0.0.8.dist-info/entry_points.txt
llama_prompt_ops-0.0.8.dist-info/top_level.txt
llama_prompt_ops-0.0.8.dist-info/RECORD
