Metadata-Version: 2.4
Name: llama-prompt-ops
Version: 0.0.8
Summary: A tool for migrating and optimizing prompts
License: MIT
Classifier: Programming Language :: Python :: 3
Classifier: Programming Language :: Python :: 3.9
Classifier: License :: OSI Approved :: MIT License
Classifier: Operating System :: OS Independent
Requires-Python: >=3.10
License-File: LICENSE
Requires-Dist: click>=8.0.0
Requires-Dist: requests>=2.25.0
Requires-Dist: dspy==2.6.13
Requires-Dist: numpy>=2.2.0
Requires-Dist: scipy>=1.15.0
Requires-Dist: pandas>=2.2.0
Requires-Dist: python-dotenv>=1.0.0
Requires-Dist: pyyaml>=6.0.0
Requires-Dist: tiktoken>=0.9.0
Requires-Dist: openai>=1.65.0
Requires-Dist: litellm>=1.63.0
Requires-Dist: huggingface-hub>=0.29.0
Requires-Dist: datasets>=2.21.0
Requires-Dist: propcache==0.3.1
Provides-Extra: dev
Requires-Dist: pytest>=8.3.0; extra == "dev"
Requires-Dist: black>=25.1.0; extra == "dev"
Requires-Dist: isort>=6.0.0; extra == "dev"
Requires-Dist: mypy>=1.15.0; extra == "dev"
Requires-Dist: tqdm>=4.67.0; extra == "dev"
Requires-Dist: jsonschema>=4.23.0; extra == "dev"
Dynamic: license-file
